Workbook

Sheet INSTRUCCIONES
A1: ANÁLISIS FINANCIERO SEMANAL — Guía de uso
A3: ESTRUCTURA
A4: Hoja | B4: Descripción
A5: INSTRUCCIONES | B5: Esta guía
A6: SEMANA_1 a SEMANA_4 | B6: Una hoja por semana del mes — cargás los datos ahí
A7: RESUMEN_MES | B7: Comparativa automática de las 4 semanas — no modificar
A9: CÓMO CARGAR CADA SEMANA
A10: 1. | B10: Abrí la hoja SEMANA_X correspondiente
A11: 2. | B11: Completá la fecha de inicio y fin de la semana (fila 3)
A12: 3. | B12: En DISPONIBILIDADES: completá el saldo al INICIO y al CIERRE de la semana
A13: 4. | B13: En EROGACIONES: completá el monto PRESUPUESTADO y el EJECUTADO
A14: 5. | B14: Las variaciones y desvíos se calculan automáticamente
A16: CONVENCIÓN DE COLORES
A17: Texto AZUL | B17: Dato a ingresar manualmente
A18: Texto VERDE | B18: Fórmula automática — no modificar
A19: Fondo AMARILLO | B19: Celda clave a actualizar

Sheet SEMANA_1
A1: ANÁLISIS FINANCIERO — SEMANA 1
A2: Semana N° | B2: 1 | C2: Fecha inicio | E2: Fecha cierre
A3: DISPONIBILIDADES (valores en USD)
A4: Variable | B4: Saldo inicio semana (USD) | C4: Saldo cierre semana (USD) | D4: Variación (USD) | E4: Variación (%) | F4: Observaciones
A5: Cheques en cartera | B5: 0 | C5: 0 | D5: =C5-B5 -> 0 | E5: =IFERROR((C5-B5)/ABS(B5),0) -> 0
A6: Banco Patagonia | B6: 0 | C6: 0 | D6: =C6-B6 -> 0 | E6: =IFERROR((C6-B6)/ABS(B6),0) -> 0
A7: Banco Francés | B7: 0 | C7: 0 | D7: =C7-B7 -> 0 | E7: =IFERROR((C7-B7)/ABS(B7),0) -> 0
A8: Banco Santander | B8: 0 | C8: 0 | D8: =C8-B8 -> 0 | E8: =IFERROR((C8-B8)/ABS(B8),0) -> 0
A9: Banco Galicia | B9: 0 | C9: 0 | D9: =C9-B9 -> 0 | E9: =IFERROR((C9-B9)/ABS(B9),0) -> 0
A10: Cobranza exportación (Estim.) | B10: 0 | C10: 0 | D10: =C10-B10 -> 0 | E10: =IFERROR((C10-B10)/ABS(B10),0) -> 0
A11: MI a cobrar (Acred. Galicia) | B11: 0 | C11: 0 | D11: =C11-B11 -> 0 | E11: =IFERROR((C11-B11)/ABS(B11),0) -> 0
A12: Divisas disponibles Patagonia | B12: 0 | C12: 0 | D12: =C12-B12 -> 0 | E12: =IFERROR((C12-B12)/ABS(B12),0) -> 0
A13: Divisas disponibles Francés | B13: 0 | C13: 0 | D13: =C13-B13 -> 0 | E13: =IFERROR((C13-B13)/ABS(B13),0) -> 0
A14: ME a cobrar | B14: 0 | C14: 0 | D14: =C14-B14 -> 0 | E14: =IFERROR((C14-B14)/ABS(B14),0) -> 0
A15: Inversiones - FCI | B15: 0 | C15: 0 | D15: =C15-B15 -> 0 | E15: =IFERROR((C15-B15)/ABS(B15),0) -> 0
A16: TOTAL DISPONIBILIDADES | B16: =SUM(B5:B15) -> 0 | C16: =SUM(C5:C15) -> 0 | D16: =C16-B16 -> 0 | E16: =IFERROR((C16-B16)/ABS(B16),0) -> 0
A18: EROGACIONES (valores en USD)
A19: Rubro | B19: Presupuestado (USD) | C19: Ejecutado (USD) | D19: Desvío (USD) | E19: Desvío (%) | F19: Observaciones
A20: Proveedores | B20: 0 | C20: 0 | D20: =C20-B20 -> 0 | E20: =IFERROR((C20-B20)/ABS(B20),0) -> 0
A21: Aranceles y Cánones | B21: 0 | C21: 0 | D21: =C21-B21 -> 0 | E21: =IFERROR((C21-B21)/ABS(B21),0) -> 0
A22: Comercio Exterior | B22: 0 | C22: 0 | D22: =C22-B22 -> 0 | E22: =IFERROR((C22-B22)/ABS(B22),0) -> 0
A23: Directores / Accionistas | B23: 0 | C23: 0 | D23: =C23-B23 -> 0 | E23: =IFERROR((C23-B23)/ABS(B23),0) -> 0
A24: Empresas del Grupo | B24: 0 | C24: 0 | D24: =C24-B24 -> 0 | E24: =IFERROR((C24-B24)/ABS(B24),0) -> 0
A25: Gastos de Buques | B25: 0 | C25: 0 | D25: =C25-B25 -> 0 | E25: =IFERROR((C25-B25)/ABS(B25),0) -> 0
A26: Impuestos y Tasas | B26: 0 | C26: 0 | D26: =C26-B26 -> 0 | E26: =IFERROR((C26-B26)/ABS(B26),0) -> 0
A27: RRHH | B27: 0 | C27: 0 | D27: =C27-B27 -> 0 | E27: =IFERROR((C27-B27)/ABS(B27),0) -> 0
A28: Servicios Varios | B28: 0 | C28: 0 | D28: =C28-B28 -> 0 | E28: =IFERROR((C28-B28)/ABS(B28),0) -> 0
A29: Retiros Particulares | B29: 0 | C29: 0 | D29: =C29-B29 -> 0 | E29: =IFERROR((C29-B29)/ABS(B29),0) -> 0
A30: Pago Importaciones | B30: 0 | C30: 0 | D30: =C30-B30 -> 0 | E30: =IFERROR((C30-B30)/ABS(B30),0) -> 0
A31: Compra Dólares (CCL) | B31: 0 | C31: 0 | D31: =C31-B31 -> 0 | E31: =IFERROR((C31-B31)/ABS(B31),0) -> 0
A32: Pago Préstamos | B32: 0 | C32: 0 | D32: =C32-B32 -> 0 | E32: =IFERROR((C32-B32)/ABS(B32),0) -> 0
A33: TOTAL EROGACIONES | B33: =SUM(B20:B32) -> 0 | C33: =SUM(C20:C32) -> 0 | D33: =C33-B33 -> 0 | E33: =IFERROR((C33-B33)/ABS(B33),0) -> 0

Sheet SEMANA_2
A1: ANÁLISIS FINANCIERO — SEMANA 2
A2: Semana N° | B2: 2 | C2: Fecha inicio | E2: Fecha cierre
A3: DISPONIBILIDADES (valores en USD)
A4: Variable | B4: Saldo inicio semana (USD) | C4: Saldo cierre semana (USD) | D4: Variación (USD) | E4: Variación (%) | F4: Observaciones
A5: Cheques en cartera | B5: 0 | C5: 0 | D5: =C5-B5 -> 0 | E5: =IFERROR((C5-B5)/ABS(B5),0) -> 0
A6: Banco Patagonia | B6: 0 | C6: 0 | D6: =C6-B6 -> 0 | E6: =IFERROR((C6-B6)/ABS(B6),0) -> 0
A7: Banco Francés | B7: 0 | C7: 0 | D7: =C7-B7 -> 0 | E7: =IFERROR((C7-B7)/ABS(B7),0) -> 0
A8: Banco Santander | B8: 0 | C8: 0 | D8: =C8-B8 -> 0 | E8: =IFERROR((C8-B8)/ABS(B8),0) -> 0
A9: Banco Galicia | B9: 0 | C9: 0 | D9: =C9-B9 -> 0 | E9: =IFERROR((C9-B9)/ABS(B9),0) -> 0
A10: Cobranza exportación (Estim.) | B10: 0 | C10: 0 | D10: =C10-B10 -> 0 | E10: =IFERROR((C10-B10)/ABS(B10),0) -> 0
A11: MI a cobrar (Acred. Galicia) | B11: 0 | C11: 0 | D11: =C11-B11 -> 0 | E11: =IFERROR((C11-B11)/ABS(B11),0) -> 0
A12: Divisas disponibles Patagonia | B12: 0 | C12: 0 | D12: =C12-B12 -> 0 | E12: =IFERROR((C12-B12)/ABS(B12),0) -> 0
A13: Divisas disponibles Francés | B13: 0 | C13: 0 | D13: =C13-B13 -> 0 | E13: =IFERROR((C13-B13)/ABS(B13),0) -> 0
A14: ME a cobrar | B14: 0 | C14: 0 | D14: =C14-B14 -> 0 | E14: =IFERROR((C14-B14)/ABS(B14),0) -> 0
A15: Inversiones - FCI | B15: 0 | C15: 0 | D15: =C15-B15 -> 0 | E15: =IFERROR((C15-B15)/ABS(B15),0) -> 0
A16: TOTAL DISPONIBILIDADES | B16: =SUM(B5:B15) -> 0 | C16: =SUM(C5:C15) -> 0 | D16: =C16-B16 -> 0 | E16: =IFERROR((C16-B16)/ABS(B16),0) -> 0
A18: EROGACIONES (valores en USD)
A19: Rubro | B19: Presupuestado (USD) | C19: Ejecutado (USD) | D19: Desvío (USD) | E19: Desvío (%) | F19: Observaciones
A20: Proveedores | B20: 0 | C20: 0 | D20: =C20-B20 -> 0 | E20: =IFERROR((C20-B20)/ABS(B20),0) -> 0
A21: Aranceles y Cánones | B21: 0 | C21: 0 | D21: =C21-B21 -> 0 | E21: =IFERROR((C21-B21)/ABS(B21),0) -> 0
A22: Comercio Exterior | B22: 0 | C22: 0 | D22: =C22-B22 -> 0 | E22: =IFERROR((C22-B22)/ABS(B22),0) -> 0
A23: Directores / Accionistas | B23: 0 | C23: 0 | D23: =C23-B23 -> 0 | E23: =IFERROR((C23-B23)/ABS(B23),0) -> 0
A24: Empresas del Grupo | B24: 0 | C24: 0 | D24: =C24-B24 -> 0 | E24: =IFERROR((C24-B24)/ABS(B24),0) -> 0
A25: Gastos de Buques | B25: 0 | C25: 0 | D25: =C25-B25 -> 0 | E25: =IFERROR((C25-B25)/ABS(B25),0) -> 0
A26: Impuestos y Tasas | B26: 0 | C26: 0 | D26: =C26-B26 -> 0 | E26: =IFERROR((C26-B26)/ABS(B26),0) -> 0
A27: RRHH | B27: 0 | C27: 0 | D27: =C27-B27 -> 0 | E27: =IFERROR((C27-B27)/ABS(B27),0) -> 0
A28: Servicios Varios | B28: 0 | C28: 0 | D28: =C28-B28 -> 0 | E28: =IFERROR((C28-B28)/ABS(B28),0) -> 0
A29: Retiros Particulares | B29: 0 | C29: 0 | D29: =C29-B29 -> 0 | E29: =IFERROR((C29-B29)/ABS(B29),0) -> 0
A30: Pago Importaciones | B30: 0 | C30: 0 | D30: =C30-B30 -> 0 | E30: =IFERROR((C30-B30)/ABS(B30),0) -> 0
A31: Compra Dólares (CCL) | B31: 0 | C31: 0 | D31: =C31-B31 -> 0 | E31: =IFERROR((C31-B31)/ABS(B31),0) -> 0
A32: Pago Préstamos | B32: 0 | C32: 0 | D32: =C32-B32 -> 0 | E32: =IFERROR((C32-B32)/ABS(B32),0) -> 0
A33: TOTAL EROGACIONES | B33: =SUM(B20:B32) -> 0 | C33: =SUM(C20:C32) -> 0 | D33: =C33-B33 -> 0 | E33: =IFERROR((C33-B33)/ABS(B33),0) -> 0

Sheet SEMANA_3
A1: ANÁLISIS FINANCIERO — SEMANA 3
A2: Semana N° | B2: 3 | C2: Fecha inicio | E2: Fecha cierre
A3: DISPONIBILIDADES (valores en USD)
A4: Variable | B4: Saldo inicio semana (USD) | C4: Saldo cierre semana (USD) | D4: Variación (USD) | E4: Variación (%) | F4: Observaciones
A5: Cheques en cartera | B5: 0 | C5: 0 | D5: =C5-B5 -> 0 | E5: =IFERROR((C5-B5)/ABS(B5),0) -> 0
A6: Banco Patagonia | B6: 0 | C6: 0 | D6: =C6-B6 -> 0 | E6: =IFERROR((C6-B6)/ABS(B6),0) -> 0
A7: Banco Francés | B7: 0 | C7: 0 | D7: =C7-B7 -> 0 | E7: =IFERROR((C7-B7)/ABS(B7),0) -> 0
A8: Banco Santander | B8: 0 | C8: 0 | D8: =C8-B8 -> 0 | E8: =IFERROR((C8-B8)/ABS(B8),0) -> 0
A9: Banco Galicia | B9: 0 | C9: 0 | D9: =C9-B9 -> 0 | E9: =IFERROR((C9-B9)/ABS(B9),0) -> 0
A10: Cobranza exportación (Estim.) | B10: 0 | C10: 0 | D10: =C10-B10 -> 0 | E10: =IFERROR((C10-B10)/ABS(B10),0) -> 0
A11: MI a cobrar (Acred. Galicia) | B11: 0 | C11: 0 | D11: =C11-B11 -> 0 | E11: =IFERROR((C11-B11)/ABS(B11),0) -> 0
A12: Divisas disponibles Patagonia | B12: 0 | C12: 0 | D12: =C12-B12 -> 0 | E12: =IFERROR((C12-B12)/ABS(B12),0) -> 0
A13: Divisas disponibles Francés | B13: 0 | C13: 0 | D13: =C13-B13 -> 0 | E13: =IFERROR((C13-B13)/ABS(B13),0) -> 0
A14: ME a cobrar | B14: 0 | C14: 0 | D14: =C14-B14 -> 0 | E14: =IFERROR((C14-B14)/ABS(B14),0) -> 0
A15: Inversiones - FCI | B15: 0 | C15: 0 | D15: =C15-B15 -> 0 | E15: =IFERROR((C15-B15)/ABS(B15),0) -> 0
A16: TOTAL DISPONIBILIDADES | B16: =SUM(B5:B15) -> 0 | C16: =SUM(C5:C15) -> 0 | D16: =C16-B16 -> 0 | E16: =IFERROR((C16-B16)/ABS(B16),0) -> 0
A18: EROGACIONES (valores en USD)
A19: Rubro | B19: Presupuestado (USD) | C19: Ejecutado (USD) | D19: Desvío (USD) | E19: Desvío (%) | F19: Observaciones
A20: Proveedores | B20: 0 | C20: 0 | D20: =C20-B20 -> 0 | E20: =IFERROR((C20-B20)/ABS(B20),0) -> 0
A21: Aranceles y Cánones | B21: 0 | C21: 0 | D21: =C21-B21 -> 0 | E21: =IFERROR((C21-B21)/ABS(B21),0) -> 0
A22: Comercio Exterior | B22: 0 | C22: 0 | D22: =C22-B22 -> 0 | E22: =IFERROR((C22-B22)/ABS(B22),0) -> 0
A23: Directores / Accionistas | B23: 0 | C23: 0 | D23: =C23-B23 -> 0 | E23: =IFERROR((C23-B23)/ABS(B23),0) -> 0
A24: Empresas del Grupo | B24: 0 | C24: 0 | D24: =C24-B24 -> 0 | E24: =IFERROR((C24-B24)/ABS(B24),0) -> 0
A25: Gastos de Buques | B25: 0 | C25: 0 | D25: =C25-B25 -> 0 | E25: =IFERROR((C25-B25)/ABS(B25),0) -> 0
A26: Impuestos y Tasas | B26: 0 | C26: 0 | D26: =C26-B26 -> 0 | E26: =IFERROR((C26-B26)/ABS(B26),0) -> 0
A27: RRHH | B27: 0 | C27: 0 | D27: =C27-B27 -> 0 | E27: =IFERROR((C27-B27)/ABS(B27),0) -> 0
A28: Servicios Varios | B28: 0 | C28: 0 | D28: =C28-B28 -> 0 | E28: =IFERROR((C28-B28)/ABS(B28),0) -> 0
A29: Retiros Particulares | B29: 0 | C29: 0 | D29: =C29-B29 -> 0 | E29: =IFERROR((C29-B29)/ABS(B29),0) -> 0
A30: Pago Importaciones | B30: 0 | C30: 0 | D30: =C30-B30 -> 0 | E30: =IFERROR((C30-B30)/ABS(B30),0) -> 0
A31: Compra Dólares (CCL) | B31: 0 | C31: 0 | D31: =C31-B31 -> 0 | E31: =IFERROR((C31-B31)/ABS(B31),0) -> 0
A32: Pago Préstamos | B32: 0 | C32: 0 | D32: =C32-B32 -> 0 | E32: =IFERROR((C32-B32)/ABS(B32),0) -> 0
A33: TOTAL EROGACIONES | B33: =SUM(B20:B32) -> 0 | C33: =SUM(C20:C32) -> 0 | D33: =C33-B33 -> 0 | E33: =IFERROR((C33-B33)/ABS(B33),0) -> 0

Sheet SEMANA_4
A1: ANÁLISIS FINANCIERO — SEMANA 4
A2: Semana N° | B2: 4 | C2: Fecha inicio | E2: Fecha cierre
A3: DISPONIBILIDADES (valores en USD)
A4: Variable | B4: Saldo inicio semana (USD) | C4: Saldo cierre semana (USD) | D4: Variación (USD) | E4: Variación (%) | F4: Observaciones
A5: Cheques en cartera | B5: 0 | C5: 0 | D5: =C5-B5 -> 0 | E5: =IFERROR((C5-B5)/ABS(B5),0) -> 0
A6: Banco Patagonia | B6: 0 | C6: 0 | D6: =C6-B6 -> 0 | E6: =IFERROR((C6-B6)/ABS(B6),0) -> 0
A7: Banco Francés | B7: 0 | C7: 0 | D7: =C7-B7 -> 0 | E7: =IFERROR((C7-B7)/ABS(B7),0) -> 0
A8: Banco Santander | B8: 0 | C8: 0 | D8: =C8-B8 -> 0 | E8: =IFERROR((C8-B8)/ABS(B8),0) -> 0
A9: Banco Galicia | B9: 0 | C9: 0 | D9: =C9-B9 -> 0 | E9: =IFERROR((C9-B9)/ABS(B9),0) -> 0
A10: Cobranza exportación (Estim.) | B10: 0 | C10: 0 | D10: =C10-B10 -> 0 | E10: =IFERROR((C10-B10)/ABS(B10),0) -> 0
A11: MI a cobrar (Acred. Galicia) | B11: 0 | C11: 0 | D11: =C11-B11 -> 0 | E11: =IFERROR((C11-B11)/ABS(B11),0) -> 0
A12: Divisas disponibles Patagonia | B12: 0 | C12: 0 | D12: =C12-B12 -> 0 | E12: =IFERROR((C12-B12)/ABS(B12),0) -> 0
A13: Divisas disponibles Francés | B13: 0 | C13: 0 | D13: =C13-B13 -> 0 | E13: =IFERROR((C13-B13)/ABS(B13),0) -> 0
A14: ME a cobrar | B14: 0 | C14: 0 | D14: =C14-B14 -> 0 | E14: =IFERROR((C14-B14)/ABS(B14),0) -> 0
A15: Inversiones - FCI | B15: 0 | C15: 0 | D15: =C15-B15 -> 0 | E15: =IFERROR((C15-B15)/ABS(B15),0) -> 0
A16: TOTAL DISPONIBILIDADES | B16: =SUM(B5:B15) -> 0 | C16: =SUM(C5:C15) -> 0 | D16: =C16-B16 -> 0 | E16: =IFERROR((C16-B16)/ABS(B16),0) -> 0
A18: EROGACIONES (valores en USD)
A19: Rubro | B19: Presupuestado (USD) | C19: Ejecutado (USD) | D19: Desvío (USD) | E19: Desvío (%) | F19: Observaciones
A20: Proveedores | B20: 0 | C20: 0 | D20: =C20-B20 -> 0 | E20: =IFERROR((C20-B20)/ABS(B20),0) -> 0
A21: Aranceles y Cánones | B21: 0 | C21: 0 | D21: =C21-B21 -> 0 | E21: =IFERROR((C21-B21)/ABS(B21),0) -> 0
A22: Comercio Exterior | B22: 0 | C22: 0 | D22: =C22-B22 -> 0 | E22: =IFERROR((C22-B22)/ABS(B22),0) -> 0
A23: Directores / Accionistas | B23: 0 | C23: 0 | D23: =C23-B23 -> 0 | E23: =IFERROR((C23-B23)/ABS(B23),0) -> 0
A24: Empresas del Grupo | B24: 0 | C24: 0 | D24: =C24-B24 -> 0 | E24: =IFERROR((C24-B24)/ABS(B24),0) -> 0
A25: Gastos de Buques | B25: 0 | C25: 0 | D25: =C25-B25 -> 0 | E25: =IFERROR((C25-B25)/ABS(B25),0) -> 0
A26: Impuestos y Tasas | B26: 0 | C26: 0 | D26: =C26-B26 -> 0 | E26: =IFERROR((C26-B26)/ABS(B26),0) -> 0
A27: RRHH | B27: 0 | C27: 0 | D27: =C27-B27 -> 0 | E27: =IFERROR((C27-B27)/ABS(B27),0) -> 0
A28: Servicios Varios | B28: 0 | C28: 0 | D28: =C28-B28 -> 0 | E28: =IFERROR((C28-B28)/ABS(B28),0) -> 0
A29: Retiros Particulares | B29: 0 | C29: 0 | D29: =C29-B29 -> 0 | E29: =IFERROR((C29-B29)/ABS(B29),0) -> 0
A30: Pago Importaciones | B30: 0 | C30: 0 | D30: =C30-B30 -> 0 | E30: =IFERROR((C30-B30)/ABS(B30),0) -> 0
A31: Compra Dólares (CCL) | B31: 0 | C31: 0 | D31: =C31-B31 -> 0 | E31: =IFERROR((C31-B31)/ABS(B31),0) -> 0
A32: Pago Préstamos | B32: 0 | C32: 0 | D32: =C32-B32 -> 0 | E32: =IFERROR((C32-B32)/ABS(B32),0) -> 0
A33: TOTAL EROGACIONES | B33: =SUM(B20:B32) -> 0 | C33: =SUM(C20:C32) -> 0 | D33: =C33-B33 -> 0 | E33: =IFERROR((C33-B33)/ABS(B33),0) -> 0

Sheet RESUMEN_MES
A1: RESUMEN MENSUAL — Comparativa de las 4 semanas
A2: Variable | B2: Semana 1 | C2: Semana 2 | D2: Semana 3 | E2: Semana 4 | F2: Δ Total
A3: DISPONIBILIDADES — Saldo al cierre de cada semana (USD)
A4: Cheques en cartera | B4: =SEMANA_1!C5 -> 0 | C4: =SEMANA_2!C5 -> 0 | D4: =SEMANA_3!C5 -> 0 | E4: =SEMANA_4!C5 -> 0 | F4: =SEMANA_4!C5-SEMANA_1!B5 -> 0
A5: Banco Patagonia | B5: =SEMANA_1!C6 -> 0 | C5: =SEMANA_2!C6 -> 0 | D5: =SEMANA_3!C6 -> 0 | E5: =SEMANA_4!C6 -> 0 | F5: =SEMANA_4!C6-SEMANA_1!B6 -> 0
A6: Banco Francés | B6: =SEMANA_1!C7 -> 0 | C6: =SEMANA_2!C7 -> 0 | D6: =SEMANA_3!C7 -> 0 | E6: =SEMANA_4!C7 -> 0 | F6: =SEMANA_4!C7-SEMANA_1!B7 -> 0
A7: Banco Santander | B7: =SEMANA_1!C8 -> 0 | C7: =SEMANA_2!C8 -> 0 | D7: =SEMANA_3!C8 -> 0 | E7: =SEMANA_4!C8 -> 0 | F7: =SEMANA_4!C8-SEMANA_1!B8 -> 0
A8: Banco Galicia | B8: =SEMANA_1!C9 -> 0 | C8: =SEMANA_2!C9 -> 0 | D8: =SEMANA_3!C9 -> 0 | E8: =SEMANA_4!C9 -> 0 | F8: =SEMANA_4!C9-SEMANA_1!B9 -> 0
A9: Cobranza exportación (Estim.) | B9: =SEMANA_1!C10 -> 0 | C9: =SEMANA_2!C10 -> 0 | D9: =SEMANA_3!C10 -> 0 | E9: =SEMANA_4!C10 -> 0 | F9: =SEMANA_4!C10-SEMANA_1!B10 -> 0
A10: MI a cobrar (Acred. Galicia) | B10: =SEMANA_1!C11 -> 0 | C10: =SEMANA_2!C11 -> 0 | D10: =SEMANA_3!C11 -> 0 | E10: =SEMANA_4!C11 -> 0 | F10: =SEMANA_4!C11-SEMANA_1!B11 -> 0
A11: Divisas disponibles Patagonia | B11: =SEMANA_1!C12 -> 0 | C11: =SEMANA_2!C12 -> 0 | D11: =SEMANA_3!C12 -> 0 | E11: =SEMANA_4!C12 -> 0 | F11: =SEMANA_4!C12-SEMANA_1!B12 -> 0
A12: Divisas disponibles Francés | B12: =SEMANA_1!C13 -> 0 | C12: =SEMANA_2!C13 -> 0 | D12: =SEMANA_3!C13 -> 0 | E12: =SEMANA_4!C13 -> 0 | F12: =SEMANA_4!C13-SEMANA_1!B13 -> 0
A13: ME a cobrar | B13: =SEMANA_1!C14 -> 0 | C13: =SEMANA_2!C14 -> 0 | D13: =SEMANA_3!C14 -> 0 | E13: =SEMANA_4!C14 -> 0 | F13: =SEMANA_4!C14-SEMANA_1!B14 -> 0
A14: Inversiones - FCI | B14: =SEMANA_1!C15 -> 0 | C14: =SEMANA_2!C15 -> 0 | D14: =SEMANA_3!C15 -> 0 | E14: =SEMANA_4!C15 -> 0 | F14: =SEMANA_4!C15-SEMANA_1!B15 -> 0
A15: TOTAL DISPONIBILIDADES | B15: =SEMANA_1!C16 -> 0 | C15: =SEMANA_2!C16 -> 0 | D15: =SEMANA_3!C16 -> 0 | E15: =SEMANA_4!C16 -> 0 | F15: =SEMANA_4!C16-SEMANA_1!B16 -> 0
A17: EROGACIONES — Ejecutado por semana (USD)
A18: Rubro | B18: Semana 1 | C18: Semana 2 | D18: Semana 3 | E18: Semana 4 | F18: Total mes
A19: Proveedores | B19: =SEMANA_1!C20 -> 0 | C19: =SEMANA_2!C20 -> 0 | D19: =SEMANA_3!C20 -> 0 | E19: =SEMANA_4!C20 -> 0 | F19: =SUM(B19:E19) -> 0
A20: Aranceles y Cánones | B20: =SEMANA_1!C21 -> 0 | C20: =SEMANA_2!C21 -> 0 | D20: =SEMANA_3!C21 -> 0 | E20: =SEMANA_4!C21 -> 0 | F20: =SUM(B20:E20) -> 0
A21: Comercio Exterior | B21: =SEMANA_1!C22 -> 0 | C21: =SEMANA_2!C22 -> 0 | D21: =SEMANA_3!C22 -> 0 | E21: =SEMANA_4!C22 -> 0 | F21: =SUM(B21:E21) -> 0
A22: Directores / Accionistas | B22: =SEMANA_1!C23 -> 0 | C22: =SEMANA_2!C23 -> 0 | D22: =SEMANA_3!C23 -> 0 | E22: =SEMANA_4!C23 -> 0 | F22: =SUM(B22:E22) -> 0
A23: Empresas del Grupo | B23: =SEMANA_1!C24 -> 0 | C23: =SEMANA_2!C24 -> 0 | D23: =SEMANA_3!C24 -> 0 | E23: =SEMANA_4!C24 -> 0 | F23: =SUM(B23:E23) -> 0
A24: Gastos de Buques | B24: =SEMANA_1!C25 -> 0 | C24: =SEMANA_2!C25 -> 0 | D24: =SEMANA_3!C25 -> 0 | E24: =SEMANA_4!C25 -> 0 | F24: =SUM(B24:E24) -> 0
A25: Impuestos y Tasas | B25: =SEMANA_1!C26 -> 0 | C25: =SEMANA_2!C26 -> 0 | D25: =SEMANA_3!C26 -> 0 | E25: =SEMANA_4!C26 -> 0 | F25: =SUM(B25:E25) -> 0
A26: RRHH | B26: =SEMANA_1!C27 -> 0 | C26: =SEMANA_2!C27 -> 0 | D26: =SEMANA_3!C27 -> 0 | E26: =SEMANA_4!C27 -> 0 | F26: =SUM(B26:E26) -> 0
A27: Servicios Varios | B27: =SEMANA_1!C28 -> 0 | C27: =SEMANA_2!C28 -> 0 | D27: =SEMANA_3!C28 -> 0 | E27: =SEMANA_4!C28 -> 0 | F27: =SUM(B27:E27) -> 0
A28: Retiros Particulares | B28: =SEMANA_1!C29 -> 0 | C28: =SEMANA_2!C29 -> 0 | D28: =SEMANA_3!C29 -> 0 | E28: =SEMANA_4!C29 -> 0 | F28: =SUM(B28:E28) -> 0
A29: Pago Importaciones | B29: =SEMANA_1!C30 -> 0 | C29: =SEMANA_2!C30 -> 0 | D29: =SEMANA_3!C30 -> 0 | E29: =SEMANA_4!C30 -> 0 | F29: =SUM(B29:E29) -> 0
A30: Compra Dólares (CCL) | B30: =SEMANA_1!C31 -> 0 | C30: =SEMANA_2!C31 -> 0 | D30: =SEMANA_3!C31 -> 0 | E30: =SEMANA_4!C31 -> 0 | F30: =SUM(B30:E30) -> 0
... A32: TOTAL EROGACIONES | B32: =SEMANA_1!C33 -> 0 | C32: =SEMANA_2!C33 -> 0 | D32: =SEMANA_3!C33 -> 0 | E32: =SEMANA_4!C33 -> 0 | F32: =SUM(B32:E32) -> 0
A34: SALDO NETO (Disponibilidades - Erogaciones ejecutadas)
A35: Saldo neto (USD) | B35: =SEMANA_1!C16-SEMANA_1!C33 -> 0 | C35: =SEMANA_2!C16-SEMANA_2!C33 -> 0 | D35: =SEMANA_3!C16-SEMANA_3!C33 -> 0 | E35: =SEMANA_4!C16-SEMANA_4!C33 -> 0 | F35: =SUM(B35:E35) -> 0
